rebelbase/VERSION
rebelbase/__init__.py
rebelbase/base2.py
rebelbase/base26c.py
rebelbase/base3.py
rebelbase/log.py
rebelbase/number.py
rebelbase/py.typed
rebelbase/value.py
rebelbase-1.0.0a7.dist-info/LICENSE
rebelbase-1.0.0a7.dist-info/METADATA
rebelbase-1.0.0a7.dist-info/WHEEL
rebelbase-1.0.0a7.dist-info/top_level.txt
rebelbase-1.0.0a7.dist-info/RECORD
