Metadata-Version: 2.1
Name: rebelbase
Version: 1.0.0a7
Summary: Recruit numbers to any base
Home-page: https://rebelbase.dev
Author: Cariad Eccleston
Author-email: cariad@cariad.earth
License: MIT
Project-URL: Documentation, https://rebelbase.dev
Project-URL: Funding, https://github.com/sponsors/cariad
Project-URL: Issues, https://github.com/cariad/rebelbase/issues
Project-URL: Source, https://github.com/cariad/rebelbase
Classifier: Development Status :: 3 - Alpha
Classifier: License :: OSI Approved :: MIT License
Classifier: Natural Language :: English
Classifier: Operating System :: OS Independent
Classifier: Programming Language :: Python :: 3 :: Only
Classifier: Programming Language :: Python :: 3.10
Classifier: Programming Language :: Python :: 3.11
Classifier: Programming Language :: Python :: 3.9
Classifier: Typing :: Typed
Requires-Python: >=3.9
License-File: LICENSE
